databind/core/__init__.py
databind/core/context.py
databind/core/converter.py
databind/core/dataclasses.py
databind/core/dataclasses.pyi
databind/core/mapper.py
databind/core/py.typed
databind/core/schema.py
databind/core/settings.py
databind/core/union.py
databind/core/utils.py
databind_core2-4.2.2.dist-info/WHEEL
databind_core2-4.2.2.dist-info/METADATA
databind_core2-4.2.2.dist-info/RECORD
